src/__init__.py
src/__main__.py
src/upf.py
upfpy/__init__.py
upfpy/__main__.py
upfpy/upf.py
upfpy-0.0.10.dist-info/LICENSE.txt
upfpy-0.0.10.dist-info/LICENSE.txt~
upfpy-0.0.10.dist-info/METADATA
upfpy-0.0.10.dist-info/WHEEL
upfpy-0.0.10.dist-info/entry_points.txt
upfpy-0.0.10.dist-info/top_level.txt
upfpy-0.0.10.dist-info/RECORD
