Metadata-Version: 2.1
Name: upfpy
Version: 0.0.10
Summary: Fully factors given integer: unique prime factorization
Home-page: https://github.com/rickhonda/upfpy
Author: Rick Honda
Author-email: rickhonda7@gmail.com
License: UNKNOWN
Platform: UNKNOWN
Classifier: Programming Language :: Python :: 2.7
Classifier: Programming Language :: Python :: 3.6
Classifier: Programming Language :: Python :: 3.7
Classifier: Programming Language :: Python :: 3.8
Classifier: License :: OSI Approved :: MIT License
Classifier: Operating System :: OS Independent
Provides-Extra: dev
Requires-Dist: pytest (>=3.8) ; extra == 'dev'
